sqlfuzz
