Metadata-Version: 2.1
Name: sqlfuzz
Version: 0.1
Summary: Random Sqlalchemy Query Generator
Home-page: https://github.com/luke9kim8/sqlfuzz
Download-URL: https://github.com/user/reponame/archive/v_01.tar.gz
Author: Wooseok Kim
Author-email: luke9kim8@gmail.com
License: MIT
Keywords: SOME,MEANINGFULL,KEYWORDS
Classifier: Development Status :: 3 - Alpha
Classifier: Intended Audience :: Developers
Classifier: Topic :: Software Development :: Build Tools
Classifier: License :: OSI Approved :: MIT License
Classifier: Programming Language :: Python :: 3
Classifier: Programming Language :: Python :: 3.4
Classifier: Programming Language :: Python :: 3.5
Classifier: Programming Language :: Python :: 3.6
License-File: LICENSE.txt
